MANIFEST.in
README.md
lammps.cfg
setup.cfg
setup.py
lammps/__init__.py
lammps/__main__.py
lammps/core.pyd
lammps/core.pyx
lammps/potential.py
lammps_cython.egg-info/PKG-INFO
lammps_cython.egg-info/SOURCES.txt
lammps_cython.egg-info/dependency_links.txt
lammps_cython.egg-info/entry_points.txt
lammps_cython.egg-info/requires.txt
lammps_cython.egg-info/top_level.txt