Metadata-Version: 2.1
Name: lammps-cython
Version: 0.6.2
Summary: Pythonic Wrapper to LAMMPS using cython
Home-page: https://gitlab.com/costrouc/lammps-cython
Author: Christopher Ostrouchov
Author-email: chris.ostrouchov+lammps@gmail.com
License: MIT
Download-URL: https://gitlab.com/costrouc/lammps-cython/-/archive/master/lammps-cython-master.zip
Keywords: lammps,molecular dynamics,cython,wrapper,mpi
Platform: UNKNOWN
Classifier: Development Status :: 3 - Alpha
Classifier: Natural Language :: English
Classifier: License :: OSI Approved :: MIT License
Classifier: Programming Language :: Python :: 3.3
Classifier: Programming Language :: Python :: 3.4
Classifier: Programming Language :: Python :: 3.5
Classifier: Programming Language :: Python :: 3.6
Provides-Extra: docs
Provides-Extra: all
Provides-Extra: gsd
Provides-Extra: ase
Provides-Extra: pymatgen
